pprint_stat/__init__.py
pprint_stat/__main__.py
pprint_stat/cli.py
pprint_stat/data.py
pprint_stat/pprint_stat.py
pprint_stat-0.1.0.dist-info/licenses/LICENSE
pprint_stat-0.1.0.dist-info/METADATA
pprint_stat-0.1.0.dist-info/WHEEL
pprint_stat-0.1.0.dist-info/entry_points.txt
pprint_stat-0.1.0.dist-info/top_level.txt
pprint_stat-0.1.0.dist-info/RECORD
